sslog/__init__.py
sslog/logger.py
utc_simple_log-0.0.5.dist-info/LICENSE
utc_simple_log-0.0.5.dist-info/METADATA
utc_simple_log-0.0.5.dist-info/WHEEL
utc_simple_log-0.0.5.dist-info/top_level.txt
utc_simple_log-0.0.5.dist-info/RECORD
