Metadata-Version: 2.1
Name: utc-simple-log
Version: 0.0.5
Summary: Simple log wrapping python logging module
Home-page: https://github.com/ppd0523/utc-simple-log.git
Author: Park Donghyeon
Author-email: emma415g@gmail.com
License: MIT
Platform: UNKNOWN
Classifier: Programming Language :: Python :: 3.6
Classifier: License :: OSI Approved :: MIT License
Requires-Python: >=3.6
Requires-Dist: pytz
